easyjapanese/__init__.py
easyjapanese/complete.py
easyjapanese/easy.py
easyjapanese/regular.py
easyjapanese-0.1.4.dist-info/LICENSE
easyjapanese-0.1.4.dist-info/METADATA
easyjapanese-0.1.4.dist-info/WHEEL
easyjapanese-0.1.4.dist-info/top_level.txt
easyjapanese-0.1.4.dist-info/RECORD
